{
	"code": 1,
	"msg": {
		"pinpai": "飞科公司创建于1999年，历经近10多年的跨越式发展，现已成为一家以“技术研发”和“品牌运营”为核心竞争力，集剃须刀及小家电研发、制造、销售于一体的企业。飞科集团现拥有100多项自主创新技术；是剃须刀国家标准起草单位。",
		"dianpu": "飞科",
		"logo": "http:\/\/img03.taobaocdn.com:80\/tfscom\/TB1Tr_VDxTpK1RjSZFGXXcHqFXa"
	},
	"time": "1608086972",
	"data": [{
		"title": "飞科电吹风家用小功率冷热风静音学生宿舍电吹风筒折叠家用旅行",
		"mainimage": "https:\/\/img.alicdn.com\/bao\/uploaded\/i2\/1715795472\/O1CN01QPl8Hu1qIDt4ifNHz_!!0-item_pic.jpg",
		"zhibo_url": "",
		"numIid": 568765562207,
		"price": "59.00",
		"couponPrice": "44.00",
		"couponRate": 7.46,
		"couponAmount": "15",
		"commissionRate": "20.00",
		"commission": "4.70",
		"small_images": "https:\/\/img.alicdn.com\/i3\/1715795472\/O1CN011bVNlb1qIDt5cmcbS_!!1715795472.jpg|https:\/\/img.alicdn.com\/i4\/1715795472\/TB2v8XxoQOWBuNjSsppXXXPgpXa_!!1715795472.jpg|https:\/\/img.alicdn.com\/i3\/1715795472\/TB2Y.04oNSYBuNjSspjXXX73VXa_!!1715795472.jpg|https:\/\/img.alicdn.com\/i2\/1715795472\/TB2Nv3kXKUXBuNjt_a0XXcysXXa_!!1715795472.jpg",
		"volume": "4",
		"nick": "飞鸿电器专营店",
		"taoToken": "",
		"rank": 1,
		"couponTotalcount": "20000",
		"couponRemaincount": "20000",
		"seller_type": "1",
		"startTime": "2020-12-15",
		"endTime": "2020-12-22",
		"keywords": "",
		"description": "飞科电吹风家用小功率冷热风静音学生宿舍电吹风筒折叠家用旅行，现价只需要59.00元，领券后下单还可优惠15元，赶紧抢购吧！"
	}, {
		"title": "飞科电吹风机家用负离子护发大功率干发器冷热风理发店造型FH6272",
		"mainimage": "https:\/\/img.alicdn.com\/bao\/uploaded\/i4\/99\/O1CN01x3nU9G1CbNr2ZDLob_!!99-0-lubanu.jpg",
		"zhibo_url": "",
		"numIid": 533217066159,
		"price": "129.00",
		"couponPrice": "99.00",
		"couponRate": 7.67,
		"couponAmount": "30",
		"commissionRate": "15.01",
		"commission": "7.94",
		"small_images": "https:\/\/img.alicdn.com\/i4\/725677994\/O1CN01V3begJ28vImYIMbFS_!!725677994-0-sm.jpg|https:\/\/img.alicdn.com\/i1\/725677994\/O1CN016To4KG28vIjMKzs4B_!!725677994.jpg|https:\/\/img.alicdn.com\/i3\/725677994\/TB2UzSztr1YBuNjSszeXXablFXa_!!725677994.jpg|https:\/\/img.alicdn.com\/i3\/725677994\/TB23pSLtv9TBuNjy1zbXXXpepXa_!!725677994.jpg",
		"volume": "163",
		"nick": "天猫超市",
		"taoToken": "",
		"rank": 1,
		"couponTotalcount": "10000",
		"couponRemaincount": "9984",
		"seller_type": "1",
		"startTime": "2020-12-15",
		"endTime": "2020-12-20",
		"keywords": "",
		"description": "飞科电吹风机家用负离子护发大功率干发器冷热风理发店造型FH6272，现价只需要129.00元，领券后下单还可优惠30元，赶紧抢购吧！"
	}, {
		"title": "飞科理发器电推剪发廊儿童成人剪头发电推子充电式剃头刀FC5805",
		"mainimage": "https:\/\/img.alicdn.com\/bao\/uploaded\/i2\/2106517863\/O1CN01XoyECw27xIqslzlII_!!0-item_pic.jpg",
		"zhibo_url": "",
		"numIid": 563345005516,
		"price": "109.00",
		"couponPrice": "79.00",
		"couponRate": 7.25,
		"couponAmount": "30",
		"commissionRate": "20.00",
		"commission": "8.44",
		"small_images": "https:\/\/img.alicdn.com\/i1\/2106517863\/TB2rUwig4SYBuNjSsphXXbGvVXa_!!2106517863.jpg|https:\/\/img.alicdn.com\/i3\/2106517863\/TB2D7v9kgvD8KJjy0FlXXagBFXa_!!2106517863.jpg|https:\/\/img.alicdn.com\/i2\/2106517863\/TB2f6lMdNk98KJjSZFoXXXS6pXa_!!2106517863.jpg|https:\/\/img.alicdn.com\/i1\/2106517863\/TB2zVz.klDH8KJjy1zeXXXjepXa_!!2106517863.jpg",
		"volume": "33",
		"nick": "琅铂旺电器专营店",
		"taoToken": "",
		"rank": 1,
		"couponTotalcount": "8000",
		"couponRemaincount": "7993",
		"seller_type": "1",
		"startTime": "2020-12-15",
		"endTime": "2020-12-21",
		"keywords": "",
		"description": "飞科理发器电推剪发廊儿童成人剪头发电推子充电式剃头刀FC5805，现价只需要109.00元，领券后下单还可优惠30元，赶紧抢购吧！"
	}]
}